openf1client/__init__.py
openf1client/client.py
openf1client/models/__init__.py
openf1client/models/car_data.py
openf1client/models/driver.py
openf1client/models/interval.py
openf1client/models/lap.py
openf1client/models/location.py
openf1client/models/meeting.py
openf1client/models/pit.py
openf1client/models/position.py
openf1client/models/race_control.py
openf1client/models/session.py
openf1client/models/stint.py
openf1client/models/team_radio.py
openf1client/models/weather.py
tests/__init__.py
openf1client-0.1.0.dist-info/METADATA
openf1client-0.1.0.dist-info/WHEEL
openf1client-0.1.0.dist-info/top_level.txt
openf1client-0.1.0.dist-info/RECORD
