Metadata-Version: 2.1
Name: openf1client
Version: 0.1.0
Requires-Dist: requests >=2.25.1
Requires-Dist: pydantic >=2.6.3
